aeda/car/__init__.py
aeda/car/main.py
aeda-2022.12.20.dist-info/METADATA
aeda-2022.12.20.dist-info/WHEEL
aeda-2022.12.20.dist-info/RECORD
